{
  "name": "telemetry",
  "type": "clab",
  "clab": {
    "config": {
      "prefix": "clab",
      "mgmt": {
        "network": "clab",
        "bridge": "br-d444ed002173",
        "ipv4-subnet": "1.1.1.0/24",
        "ipv4-gw": "1.1.1.1",
        "mtu": "1500",
        "external-access": true
      }
    }
  },
  "nodes": {
    "C1": {
      "index": "0",
      "shortname": "C1",
      "longname": "clab-telemetry-C1",
      "fqdn": "C1.telemetry.io",
      "group": "",
      "labdir": "/home/adam/telemetria3/clab-telemetry/C1",
      "kind": "linux",
      "image": "alpine/iperf",
      "mgmt-net": "",
      "mgmt-intf": "",
      "mgmt-ipv4-address": "1.1.1.6",
      "mgmt-ipv4-prefix-length": 24,
      "mgmt-ipv6-address": "",
      "mgmt-ipv6-prefix-length": 0,
      "mac-address": "",
      "labels": {
        "clab-mgmt-net-bridge": "br-d444ed002173",
        "clab-node-group": "",
        "clab-node-kind": "linux",
        "clab-node-lab-dir": "/home/adam/telemetria3/clab-telemetry/C1",
        "clab-node-name": "C1",
        "clab-node-type": "",
        "clab-topo-file": "/home/adam/telemetria3/telemetry.clab.yml",
        "containerlab": "telemetry"
      }
    },
    "C2": {
      "index": "1",
      "shortname": "C2",
      "longname": "clab-telemetry-C2",
      "fqdn": "C2.telemetry.io",
      "group": "",
      "labdir": "/home/adam/telemetria3/clab-telemetry/C2",
      "kind": "linux",
      "image": "alpine/iperf",
      "mgmt-net": "",
      "mgmt-intf": "",
      "mgmt-ipv4-address": "1.1.1.3",
      "mgmt-ipv4-prefix-length": 24,
      "mgmt-ipv6-address": "",
      "mgmt-ipv6-prefix-length": 0,
      "mac-address": "",
      "labels": {
        "clab-mgmt-net-bridge": "br-d444ed002173",
        "clab-node-group": "",
        "clab-node-kind": "linux",
        "clab-node-lab-dir": "/home/adam/telemetria3/clab-telemetry/C2",
        "clab-node-name": "C2",
        "clab-node-type": "",
        "clab-topo-file": "/home/adam/telemetria3/telemetry.clab.yml",
        "containerlab": "telemetry"
      }
    },
    "C3": {
      "index": "2",
      "shortname": "C3",
      "longname": "clab-telemetry-C3",
      "fqdn": "C3.telemetry.io",
      "group": "",
      "labdir": "/home/adam/telemetria3/clab-telemetry/C3",
      "kind": "linux",
      "image": "alpine/iperf",
      "mgmt-net": "",
      "mgmt-intf": "",
      "mgmt-ipv4-address": "1.1.1.2",
      "mgmt-ipv4-prefix-length": 24,
      "mgmt-ipv6-address": "",
      "mgmt-ipv6-prefix-length": 0,
      "mac-address": "",
      "labels": {
        "clab-mgmt-net-bridge": "br-d444ed002173",
        "clab-node-group": "",
        "clab-node-kind": "linux",
        "clab-node-lab-dir": "/home/adam/telemetria3/clab-telemetry/C3",
        "clab-node-name": "C3",
        "clab-node-type": "",
        "clab-topo-file": "/home/adam/telemetria3/telemetry.clab.yml",
        "containerlab": "telemetry"
      }
    },
    "R11": {
      "index": "3",
      "shortname": "R11",
      "longname": "clab-telemetry-R11",
      "fqdn": "R11.telemetry.io",
      "group": "",
      "labdir": "/home/adam/telemetria3/clab-telemetry/R11",
      "kind": "srl",
      "image": "ghcr.io/nokia/srlinux",
      "mgmt-net": "",
      "mgmt-intf": "",
      "mgmt-ipv4-address": "1.1.1.5",
      "mgmt-ipv4-prefix-length": 24,
      "mgmt-ipv6-address": "",
      "mgmt-ipv6-prefix-length": 0,
      "mac-address": "",
      "labels": {
        "clab-mgmt-net-bridge": "br-d444ed002173",
        "clab-node-group": "",
        "clab-node-kind": "srl",
        "clab-node-lab-dir": "/home/adam/telemetria3/clab-telemetry/R11",
        "clab-node-name": "R11",
        "clab-node-type": "ixrd2",
        "clab-topo-file": "/home/adam/telemetria3/telemetry.clab.yml",
        "containerlab": "telemetry"
      }
    },
    "R12": {
      "index": "4",
      "shortname": "R12",
      "longname": "clab-telemetry-R12",
      "fqdn": "R12.telemetry.io",
      "group": "",
      "labdir": "/home/adam/telemetria3/clab-telemetry/R12",
      "kind": "srl",
      "image": "ghcr.io/nokia/srlinux",
      "mgmt-net": "",
      "mgmt-intf": "",
      "mgmt-ipv4-address": "1.1.1.4",
      "mgmt-ipv4-prefix-length": 24,
      "mgmt-ipv6-address": "",
      "mgmt-ipv6-prefix-length": 0,
      "mac-address": "",
      "labels": {
        "clab-mgmt-net-bridge": "br-d444ed002173",
        "clab-node-group": "",
        "clab-node-kind": "srl",
        "clab-node-lab-dir": "/home/adam/telemetria3/clab-telemetry/R12",
        "clab-node-name": "R12",
        "clab-node-type": "ixrd2",
        "clab-topo-file": "/home/adam/telemetria3/telemetry.clab.yml",
        "containerlab": "telemetry"
      }
    },
    "R13": {
      "index": "5",
      "shortname": "R13",
      "longname": "clab-telemetry-R13",
      "fqdn": "R13.telemetry.io",
      "group": "",
      "labdir": "/home/adam/telemetria3/clab-telemetry/R13",
      "kind": "srl",
      "image": "ghcr.io/nokia/srlinux",
      "mgmt-net": "",
      "mgmt-intf": "",
      "mgmt-ipv4-address": "1.1.1.13",
      "mgmt-ipv4-prefix-length": 24,
      "mgmt-ipv6-address": "",
      "mgmt-ipv6-prefix-length": 0,
      "mac-address": "",
      "labels": {
        "clab-mgmt-net-bridge": "br-d444ed002173",
        "clab-node-group": "",
        "clab-node-kind": "srl",
        "clab-node-lab-dir": "/home/adam/telemetria3/clab-telemetry/R13",
        "clab-node-name": "R13",
        "clab-node-type": "ixrd2",
        "clab-topo-file": "/home/adam/telemetria3/telemetry.clab.yml",
        "containerlab": "telemetry"
      }
    },
    "R14": {
      "index": "6",
      "shortname": "R14",
      "longname": "clab-telemetry-R14",
      "fqdn": "R14.telemetry.io",
      "group": "",
      "labdir": "/home/adam/telemetria3/clab-telemetry/R14",
      "kind": "srl",
      "image": "ghcr.io/nokia/srlinux",
      "mgmt-net": "",
      "mgmt-intf": "",
      "mgmt-ipv4-address": "1.1.1.11",
      "mgmt-ipv4-prefix-length": 24,
      "mgmt-ipv6-address": "",
      "mgmt-ipv6-prefix-length": 0,
      "mac-address": "",
      "labels": {
        "clab-mgmt-net-bridge": "br-d444ed002173",
        "clab-node-group": "",
        "clab-node-kind": "srl",
        "clab-node-lab-dir": "/home/adam/telemetria3/clab-telemetry/R14",
        "clab-node-name": "R14",
        "clab-node-type": "ixrd2",
        "clab-topo-file": "/home/adam/telemetria3/telemetry.clab.yml",
        "containerlab": "telemetry"
      }
    },
    "R21": {
      "index": "7",
      "shortname": "R21",
      "longname": "clab-telemetry-R21",
      "fqdn": "R21.telemetry.io",
      "group": "",
      "labdir": "/home/adam/telemetria3/clab-telemetry/R21",
      "kind": "srl",
      "image": "ghcr.io/nokia/srlinux",
      "mgmt-net": "",
      "mgmt-intf": "",
      "mgmt-ipv4-address": "1.1.1.7",
      "mgmt-ipv4-prefix-length": 24,
      "mgmt-ipv6-address": "",
      "mgmt-ipv6-prefix-length": 0,
      "mac-address": "",
      "labels": {
        "clab-mgmt-net-bridge": "br-d444ed002173",
        "clab-node-group": "",
        "clab-node-kind": "srl",
        "clab-node-lab-dir": "/home/adam/telemetria3/clab-telemetry/R21",
        "clab-node-name": "R21",
        "clab-node-type": "ixrd2",
        "clab-topo-file": "/home/adam/telemetria3/telemetry.clab.yml",
        "containerlab": "telemetry"
      }
    },
    "R22": {
      "index": "8",
      "shortname": "R22",
      "longname": "clab-telemetry-R22",
      "fqdn": "R22.telemetry.io",
      "group": "",
      "labdir": "/home/adam/telemetria3/clab-telemetry/R22",
      "kind": "srl",
      "image": "ghcr.io/nokia/srlinux",
      "mgmt-net": "",
      "mgmt-intf": "",
      "mgmt-ipv4-address": "1.1.1.10",
      "mgmt-ipv4-prefix-length": 24,
      "mgmt-ipv6-address": "",
      "mgmt-ipv6-prefix-length": 0,
      "mac-address": "",
      "labels": {
        "clab-mgmt-net-bridge": "br-d444ed002173",
        "clab-node-group": "",
        "clab-node-kind": "srl",
        "clab-node-lab-dir": "/home/adam/telemetria3/clab-telemetry/R22",
        "clab-node-name": "R22",
        "clab-node-type": "ixrd2",
        "clab-topo-file": "/home/adam/telemetria3/telemetry.clab.yml",
        "containerlab": "telemetry"
      }
    },
    "R31": {
      "index": "9",
      "shortname": "R31",
      "longname": "clab-telemetry-R31",
      "fqdn": "R31.telemetry.io",
      "group": "",
      "labdir": "/home/adam/telemetria3/clab-telemetry/R31",
      "kind": "srl",
      "image": "ghcr.io/nokia/srlinux",
      "mgmt-net": "",
      "mgmt-intf": "",
      "mgmt-ipv4-address": "1.1.1.9",
      "mgmt-ipv4-prefix-length": 24,
      "mgmt-ipv6-address": "",
      "mgmt-ipv6-prefix-length": 0,
      "mac-address": "",
      "labels": {
        "clab-mgmt-net-bridge": "br-d444ed002173",
        "clab-node-group": "",
        "clab-node-kind": "srl",
        "clab-node-lab-dir": "/home/adam/telemetria3/clab-telemetry/R31",
        "clab-node-name": "R31",
        "clab-node-type": "ixrd2",
        "clab-topo-file": "/home/adam/telemetria3/telemetry.clab.yml",
        "containerlab": "telemetry"
      }
    },
    "R32": {
      "index": "10",
      "shortname": "R32",
      "longname": "clab-telemetry-R32",
      "fqdn": "R32.telemetry.io",
      "group": "",
      "labdir": "/home/adam/telemetria3/clab-telemetry/R32",
      "kind": "srl",
      "image": "ghcr.io/nokia/srlinux",
      "mgmt-net": "",
      "mgmt-intf": "",
      "mgmt-ipv4-address": "1.1.1.12",
      "mgmt-ipv4-prefix-length": 24,
      "mgmt-ipv6-address": "",
      "mgmt-ipv6-prefix-length": 0,
      "mac-address": "",
      "labels": {
        "clab-mgmt-net-bridge": "br-d444ed002173",
        "clab-node-group": "",
        "clab-node-kind": "srl",
        "clab-node-lab-dir": "/home/adam/telemetria3/clab-telemetry/R32",
        "clab-node-name": "R32",
        "clab-node-type": "ixrd2",
        "clab-topo-file": "/home/adam/telemetria3/telemetry.clab.yml",
        "containerlab": "telemetry"
      }
    },
    "consul-agent": {
      "index": "11",
      "shortname": "consul-agent",
      "longname": "clab-telemetry-consul-agent",
      "fqdn": "consul-agent.telemetry.io",
      "group": "",
      "labdir": "/home/adam/telemetria3/clab-telemetry/consul-agent",
      "kind": "linux",
      "image": "consul:latest",
      "mgmt-net": "",
      "mgmt-intf": "",
      "mgmt-ipv4-address": "1.1.1.8",
      "mgmt-ipv4-prefix-length": 24,
      "mgmt-ipv6-address": "",
      "mgmt-ipv6-prefix-length": 0,
      "mac-address": "",
      "labels": {
        "clab-mgmt-net-bridge": "br-d444ed002173",
        "clab-node-group": "",
        "clab-node-kind": "linux",
        "clab-node-lab-dir": "/home/adam/telemetria3/clab-telemetry/consul-agent",
        "clab-node-name": "consul-agent",
        "clab-node-type": "",
        "clab-topo-file": "/home/adam/telemetria3/telemetry.clab.yml",
        "containerlab": "telemetry"
      }
    },
    "gnmic": {
      "index": "12",
      "shortname": "gnmic",
      "longname": "clab-telemetry-gnmic",
      "fqdn": "gnmic.telemetry.io",
      "group": "",
      "labdir": "/home/adam/telemetria3/clab-telemetry/gnmic",
      "kind": "linux",
      "image": "gnmic/gnmic",
      "mgmt-net": "",
      "mgmt-intf": "",
      "mgmt-ipv4-address": "1.1.1.16",
      "mgmt-ipv4-prefix-length": 24,
      "mgmt-ipv6-address": "",
      "mgmt-ipv6-prefix-length": 0,
      "mac-address": "",
      "labels": {
        "clab-mgmt-net-bridge": "br-d444ed002173",
        "clab-node-group": "",
        "clab-node-kind": "linux",
        "clab-node-lab-dir": "/home/adam/telemetria3/clab-telemetry/gnmic",
        "clab-node-name": "gnmic",
        "clab-node-type": "",
        "clab-topo-file": "/home/adam/telemetria3/telemetry.clab.yml",
        "containerlab": "telemetry"
      }
    },
    "grafana": {
      "index": "13",
      "shortname": "grafana",
      "longname": "clab-telemetry-grafana",
      "fqdn": "grafana.telemetry.io",
      "group": "",
      "labdir": "/home/adam/telemetria3/clab-telemetry/grafana",
      "kind": "linux",
      "image": "grafana/grafana-enterprise",
      "mgmt-net": "",
      "mgmt-intf": "",
      "mgmt-ipv4-address": "1.1.1.14",
      "mgmt-ipv4-prefix-length": 24,
      "mgmt-ipv6-address": "",
      "mgmt-ipv6-prefix-length": 0,
      "mac-address": "",
      "labels": {
        "clab-mgmt-net-bridge": "br-d444ed002173",
        "clab-node-group": "",
        "clab-node-kind": "linux",
        "clab-node-lab-dir": "/home/adam/telemetria3/clab-telemetry/grafana",
        "clab-node-name": "grafana",
        "clab-node-type": "",
        "clab-topo-file": "/home/adam/telemetria3/telemetry.clab.yml",
        "containerlab": "telemetry"
      }
    },
    "prometheus": {
      "index": "14",
      "shortname": "prometheus",
      "longname": "clab-telemetry-prometheus",
      "fqdn": "prometheus.telemetry.io",
      "group": "",
      "labdir": "/home/adam/telemetria3/clab-telemetry/prometheus",
      "kind": "linux",
      "image": "prom/prometheus",
      "mgmt-net": "",
      "mgmt-intf": "",
      "mgmt-ipv4-address": "1.1.1.15",
      "mgmt-ipv4-prefix-length": 24,
      "mgmt-ipv6-address": "",
      "mgmt-ipv6-prefix-length": 0,
      "mac-address": "",
      "labels": {
        "clab-mgmt-net-bridge": "br-d444ed002173",
        "clab-node-group": "",
        "clab-node-kind": "linux",
        "clab-node-lab-dir": "/home/adam/telemetria3/clab-telemetry/prometheus",
        "clab-node-name": "prometheus",
        "clab-node-type": "",
        "clab-topo-file": "/home/adam/telemetria3/telemetry.clab.yml",
        "containerlab": "telemetry"
      }
    }
  },
  "links": [
    {
      "a": {
        "node": "R11",
        "interface": "e1-2",
        "mac": "aa:c1:ab:7c:70:99",
        "peer": "z"
      },
      "z": {
        "node": "R12",
        "interface": "e1-1",
        "mac": "aa:c1:ab:90:63:35",
        "peer": "a"
      }
    },
    {
      "a": {
        "node": "R11",
        "interface": "e1-4",
        "mac": "aa:c1:ab:54:ab:55",
        "peer": "z"
      },
      "z": {
        "node": "R14",
        "interface": "e1-1",
        "mac": "aa:c1:ab:58:6b:53",
        "peer": "a"
      }
    },
    {
      "a": {
        "node": "R12",
        "interface": "e1-3",
        "mac": "aa:c1:ab:7f:97:bc",
        "peer": "z"
      },
      "z": {
        "node": "R13",
        "interface": "e1-2",
        "mac": "aa:c1:ab:9c:ab:25",
        "peer": "a"
      }
    },
    {
      "a": {
        "node": "R13",
        "interface": "e1-4",
        "mac": "aa:c1:ab:af:f2:f3",
        "peer": "z"
      },
      "z": {
        "node": "R14",
        "interface": "e1-3",
        "mac": "aa:c1:ab:32:9f:3f",
        "peer": "a"
      }
    },
    {
      "a": {
        "node": "R14",
        "interface": "e1-2",
        "mac": "aa:c1:ab:50:c4:f6",
        "peer": "z"
      },
      "z": {
        "node": "R12",
        "interface": "e1-4",
        "mac": "aa:c1:ab:e2:d5:fa",
        "peer": "a"
      }
    },
    {
      "a": {
        "node": "R21",
        "interface": "e1-2",
        "mac": "aa:c1:ab:01:ef:04",
        "peer": "z"
      },
      "z": {
        "node": "R22",
        "interface": "e1-1",
        "mac": "aa:c1:ab:0b:71:9b",
        "peer": "a"
      }
    },
    {
      "a": {
        "node": "R31",
        "interface": "e1-2",
        "mac": "aa:c1:ab:fb:72:48",
        "peer": "z"
      },
      "z": {
        "node": "R32",
        "interface": "e1-1",
        "mac": "aa:c1:ab:0e:d6:ce",
        "peer": "a"
      }
    },
    {
      "a": {
        "node": "R11",
        "interface": "e1-21",
        "mac": "aa:c1:ab:c6:19:a1",
        "peer": "z"
      },
      "z": {
        "node": "R21",
        "interface": "e1-11",
        "mac": "aa:c1:ab:e0:08:b8",
        "peer": "a"
      }
    },
    {
      "a": {
        "node": "R12",
        "interface": "e1-32",
        "mac": "aa:c1:ab:bb:05:18",
        "peer": "z"
      },
      "z": {
        "node": "R31",
        "interface": "e1-13",
        "mac": "aa:c1:ab:79:c3:f8",
        "peer": "a"
      }
    },
    {
      "a": {
        "node": "C1",
        "interface": "eth1",
        "mac": "aa:c1:ab:ba:11:59",
        "peer": "z"
      },
      "z": {
        "node": "R14",
        "interface": "e1-49",
        "mac": "aa:c1:ab:18:f9:b5",
        "peer": "a"
      }
    },
    {
      "a": {
        "node": "C2",
        "interface": "eth1",
        "mac": "aa:c1:ab:72:6a:ff",
        "peer": "z"
      },
      "z": {
        "node": "R22",
        "interface": "e1-49",
        "mac": "aa:c1:ab:bc:b2:3a",
        "peer": "a"
      }
    },
    {
      "a": {
        "node": "C3",
        "interface": "eth1",
        "mac": "aa:c1:ab:14:bc:f5",
        "peer": "z"
      },
      "z": {
        "node": "R32",
        "interface": "e1-49",
        "mac": "aa:c1:ab:8f:77:55",
        "peer": "a"
      }
    }
  ]
}
